week4/lab8/fibonacci_generator.v
module fibonacci_generator(
    input rst,
    input clk,
    input enable,
    output reg [31:0] fib_out
);

    reg [31:0] fib_prev1;
    reg [31:0] fib_prev2;

    always @(posedge clk or posedge rst) begin 
        if (rst) begin
            fib_prev1 <= 32'b1;
            fib_prev2 <= 32'b0;
            fib_out <= 32'b0;
        end else if (enable) begin
            fib_out <= fib_prev1 + fib_prev2;
            fib_prev2 <= fib_prev1;
            fib_prev1 <= fib_out;
        end
    end

endmodule

week4/lab8/fibonacci_generator.vcd
$version Generated by VerilatedVcd $end
$timescale 1ps $end
 $scope module TOP $end
  $var wire 1 # rst $end
  $var wire 1 $ clk $end
  $var wire 1 % enable $end
  $var wire 32 & fib_out [31:0] $end
  $scope module fibonacci_generator $end
   $var wire 1 # rst $end
   $var wire 1 $ clk $end
   $var wire 1 % enable $end
   $var wire 32 & fib_out [31:0] $end
   $var wire 32 ' fib_prev1 [31:0] $end
   $var wire 32 ( fib_prev2 [31:0] $end
  $upscope $end
 $upscope $end
$enddefinitions $end


#10
1#
1$
1%
b00000000000000000000000000000000 &
b00000000000000000000000000000000 '
b00000000000000000000000000000000 (
#20
0$
#30
1$
b00000000000000000000000000000001 '
#40
0$
#50
1$
#60
0$
#70
1$
#80
0$
#90
1$
#100
0$
#110
0#
1$
b00000000000000000000000000000001 &
b00000000000000000000000000000000 '
b00000000000000000000000000000001 (
#120
0$
#130
1$
b00000000000000000000000000000001 '
b00000000000000000000000000000000 (
#140
0$
#150
1$
b00000000000000000000000000000001 (
#160
0$
#170
1$
b00000000000000000000000000000010 &
#180
0$
#190
1$
b00000000000000000000000000000010 '
#200
0$
#210
1$
b00000000000000000000000000000011 &
b00000000000000000000000000000010 (
#220
0$
#230
1$
b00000000000000000000000000000100 &
b00000000000000000000000000000011 '
#240
0$
#250
1$
b00000000000000000000000000000101 &
b00000000000000000000000000000100 '
b00000000000000000000000000000011 (
#260
0$
#270
1$
b00000000000000000000000000000111 &
b00000000000000000000000000000101 '
b00000000000000000000000000000100 (
#280
0$
#290
1$
b00000000000000000000000000001001 &
b00000000000000000000000000000111 '
b00000000000000000000000000000101 (
#300
0$
#310
1$
b00000000000000000000000000001100 &
b00000000000000000000000000001001 '
b00000000000000000000000000000111 (
#320
0$
#330
1$
b00000000000000000000000000010000 &
b00000000000000000000000000001100 '
b00000000000000000000000000001001 (
#340
0$
#350
1$
b00000000000000000000000000010101 &
b00000000000000000000000000010000 '
b00000000000000000000000000001100 (
#360
0$
#370
1$
b00000000000000000000000000011100 &
b00000000000000000000000000010101 '
b00000000000000000000000000010000 (
#380
0$
#390
1$
b00000000000000000000000000100101 &
b00000000000000000000000000011100 '
b00000000000000000000000000010101 (
#400
0$
#410
1$
b00000000000000000000000000110001 &
b00000000000000000000000000100101 '
b00000000000000000000000000011100 (
#420
0$
#430
1$
b00000000000000000000000001000001 &
b00000000000000000000000000110001 '
b00000000000000000000000000100101 (
#440
0$
#450
1$
b00000000000000000000000001010110 &
b00000000000000000000000001000001 '
b00000000000000000000000000110001 (
#460
0$
#470
1$
b00000000000000000000000001110010 &
b00000000000000000000000001010110 '
b00000000000000000000000001000001 (
#480
0$
#490
1$
b00000000000000000000000010010111 &
b00000000000000000000000001110010 '
b00000000000000000000000001010110 (
#500
0$
#510
1$
b00000000000000000000000011001000 &
b00000000000000000000000010010111 '
b00000000000000000000000001110010 (
#520
0$
#530
1$
b00000000000000000000000100001001 &
b00000000000000000000000011001000 '
b00000000000000000000000010010111 (
#540
0$
#550
1$
b00000000000000000000000101011111 &
b00000000000000000000000100001001 '
b00000000000000000000000011001000 (
#560
0$
#570
1$
b00000000000000000000000111010001 &
b00000000000000000000000101011111 '
b00000000000000000000000100001001 (
#580
0$
#590
1$
b00000000000000000000001001101000 &
b00000000000000000000000111010001 '
b00000000000000000000000101011111 (
#600
0$
#610
1$
b00000000000000000000001100110000 &
b00000000000000000000001001101000 '
b00000000000000000000000111010001 (
#620
0$
#630
1$
b00000000000000000000010000111001 &
b00000000000000000000001100110000 '
b00000000000000000000001001101000 (
#640
0$
#650
1$
b00000000000000000000010110011000 &
b00000000000000000000010000111001 '
b00000000000000000000001100110000 (
#660
0$
#670
1$
b00000000000000000000011101101001 &
b00000000000000000000010110011000 '
b00000000000000000000010000111001 (
#680
0$
#690
1$
b00000000000000000000100111010001 &
b00000000000000000000011101101001 '
b00000000000000000000010110011000 (
#700
0$
#710
1$
b00000000000000000000110100000001 &
b00000000000000000000100111010001 '
b00000000000000000000011101101001 (
#720
0$
#730
1$
b00000000000000000001000100111010 &
b00000000000000000000110100000001 '
b00000000000000000000100111010001 (
#740
0$
#750
1$
b00000000000000000001011011010010 &
b00000000000000000001000100111010 '
b00000000000000000000110100000001 (
#760
0$
#770
1$
b00000000000000000001111000111011 &
b00000000000000000001011011010010 '
b00000000000000000001000100111010 (
#780
0$
#790
1$
b00000000000000000010100000001100 &
b00000000000000000001111000111011 '
b00000000000000000001011011010010 (
#800
0$
#810
1$
b00000000000000000011010100001101 &
b00000000000000000010100000001100 '
b00000000000000000001111000111011 (
#820
0$
#830
1$
b00000000000000000100011001000111 &
b00000000000000000011010100001101 '
b00000000000000000010100000001100 (
#840
0$
#850
1$
b00000000000000000101110100011001 &
b00000000000000000100011001000111 '
b00000000000000000011010100001101 (
#860
0$
#870
1$
b00000000000000000111101101010100 &
b00000000000000000101110100011001 '
b00000000000000000100011001000111 (
#880
0$
#890
1$
b00000000000000001010001101100000 &
b00000000000000000111101101010100 '
b00000000000000000101110100011001 (
#900
0$
#910
1$
b00000000000000001101100001101101 &
b00000000000000001010001101100000 '
b00000000000000000111101101010100 (
#920
0$
#930
1$
b00000000000000010001111010110100 &
b00000000000000001101100001101101 '
b00000000000000001010001101100000 (
#940
0$
#950
1$
b00000000000000010111101111001101 &
b00000000000000010001111010110100 '
b00000000000000001101100001101101 (
#960
0$
#970
1$
b00000000000000011111011100100001 &
b00000000000000010111101111001101 '
b00000000000000010001111010110100 (
#980
0$
#990
1$
b00000000000000101001101010000001 &
b00000000000000011111011100100001 '
b00000000000000010111101111001101 (
#1000
0$
#1010
1$
b00000000000000110111001011101110 &
b00000000000000101001101010000001 '
b00000000000000011111011100100001 (
#1020
0$
#1030
1$
b00000000000001001001000110100010 &
b00000000000000110111001011101110 '
b00000000000000101001101010000001 (
#1040
0$
#1050
1$
b00000000000001100000110101101111 &
b00000000000001001001000110100010 '
b00000000000000110111001011101110 (
#1060
0$
#1070
1$
b00000000000010000000010010010000 &
b00000000000001100000110101101111 '
b00000000000001001001000110100010 (
#1080
0$
#1090
1$
b00000000000010101001111100010001 &
b00000000000010000000010010010000 '
b00000000000001100000110101101111 (
#1100
0$
#1110
1$
b00000000000011100001000111111111 &
b00000000000010101001111100010001 '
b00000000000010000000010010010000 (
#1120
0$
#1130
1$
b00000000000100101010001110100001 &
b00000000000011100001000111111111 '
b00000000000010101001111100010001 (
#1140
0$
#1150
1$
b00000000000110001011000100010000 &
b00000000000100101010001110100001 '
b00000000000011100001000111111111 (
#1160
0$
#1170
1$
b00000000001000001011010110100000 &
b00000000000110001011000100010000 '
b00000000000100101010001110100001 (
#1180
0$
#1190
1$
b00000000001010110101010010110001 &
b00000000001000001011010110100000 '
b00000000000110001011000100010000 (
#1200
0$
#1210
1$
b00000000001110010110011010110000 &
b00000000001010110101010010110001 '
b00000000001000001011010110100000 (
#1220
0$
#1230
1$
b00000000010011000000101001010001 &
b00000000001110010110011010110000 '
b00000000001010110101010010110001 (
#1240
0$
#1250
1$
b00000000011001001011101101100001 &
b00000000010011000000101001010001 '
b00000000001110010110011010110000 (
#1260
0$
#1270
1$
b00000000100001010111000100000001 &
b00000000011001001011101101100001 '
b00000000010011000000101001010001 (
#1280
0$
#1290
1$
b00000000101100001100010110110010 &
b00000000100001010111000100000001 '
b00000000011001001011101101100001 (
#1300
0$
#1310
1$
b00000000111010100010110001100010 &
b00000000101100001100010110110010 '
b00000000100001010111000100000001 (
#1320
0$
#1330
1$
b00000001001101100011011010110011 &
b00000000111010100010110001100010 '
b00000000101100001100010110110010 (
#1340
0$
#1350
1$
b00000001100110101111001000010100 &
b00000001001101100011011010110011 '
b00000000111010100010110001100010 (
#1360
0$
#1370
1$
b00000010001000000110001100010101 &
b00000001100110101111001000010100 '
b00000001001101100011011010110011 (
#1380
0$
#1390
1$
b00000010110100010010100011000111 &
b00000010001000000110001100010101 '
b00000001100110101111001000010100 (
#1400
0$
#1410
1$
b00000011101110110101010100101001 &
b00000010110100010010100011000111 '
b00000010001000000110001100010101 (
#1420
0$
#1430
1$
b00000100111100011000101111011100 &
b00000011101110110101010100101001 '
b00000010110100010010100011000111 (
#1440
0$
#1450
1$
b00000110100011000111110111110000 &
b00000100111100011000101111011100 '
b00000011101110110101010100101001 (
#1460
0$
#1470
1$
b00001000101011001110000100000101 &
b00000110100011000111110111110000 '
b00000100111100011000101111011100 (
#1480
0$
#1490
1$
b00001011011111100000100111001100 &
b00001000101011001110000100000101 '
b00000110100011000111110111110000 (
#1500
0$
#1510
1$
b00001111001110010101111011110101 &
b00001011011111100000100111001100 '
b00001000101011001110000100000101 (
#1520
0$
#1530
1$
b00010100001010101110101011010001 &
b00001111001110010101111011110101 '
b00001011011111100000100111001100 (
#1540
0$
#1550
1$
b00011010101101110110100011000001 &
b00010100001010101110101011010001 '
b00001111001110010101111011110101 (
#1560
0$
#1570
1$
b00100011011001000100100111000110 &
b00011010101101110110100011000001 '
b00010100001010101110101011010001 (
#1580
0$
#1590
1$
b00101110111000100101001110010010 &
b00100011011001000100100111000110 '
b00011010101101110110100011000001 (
#1600
0$
#1610
1$
b00111110000110111011001010000111 &
b00101110111000100101001110010010 '
b00100011011001000100100111000110 (
#1620
0$
#1630
1$
b01010010010001101001110101011000 &
b00111110000110111011001010000111 '
b00101110111000100101001110010010 (
#1640
0$
#1650
1$
b01101100111111100000011000011001 &
b01010010010001101001110101011000 '
b00111110000110111011001010000111 (
#1660
0$
#1670
1$
b10010000011000100100111111011111 &
b01101100111111100000011000011001 '
b01010010010001101001110101011000 (
#1680
0$
#1690
1$
b10111111010001001010001101110001 &
b10010000011000100100111111011111 '
b01101100111111100000011000011001 (
#1700
0$
#1710
1$
b11111101011000000101010111111000 &
b10111111010001001010001101110001 '
b10010000011000100100111111011111 (
#1720
0$
#1730
1$
b01001111101001101111001101010000 &
b11111101011000000101010111111000 '
b10111111010001001010001101110001 (
#1740
0$
#1750
1$
b10111100101001001111100101101001 &
b01001111101001101111001101010000 '
b11111101011000000101010111111000 (
#1760
0$
#1770
1$
b01001101000001110100100101001000 &
b10111100101001001111100101101001 '
b01001111101001101111001101010000 (
#1780
0$
#1790
1$
b00001100010010111110110010111001 &
b01001101000001110100100101001000 '
b10111100101001001111100101101001 (
#1800
0$
#1810
1$
b00001001101011000100001010110001 &
b00001100010010111110110010111001 '
b01001101000001110100100101001000 (
#1820
0$
#1830
1$
b01011001010100110011011000000001 &
b00001001101011000100001010110001 '
b00001100010010111110110010111001 (
#1840
0$
#1850
1$
b00010101111110000010111101101010 &
b01011001010100110011011000000001 '
b00001001101011000100001010110001 (
#1860
0$
#1870
1$
b01100010111111110111100010110010 &
b00010101111110000010111101101010 '
b01011001010100110011011000000001 (
#1880
0$
#1890
1$
b01101111010010110110010101101011 &
b01100010111111110111100010110010 '
b00010101111110000010111101101010 (
#1900
0$
#1910
1$
b01111000111101111010100000011100 &
b01101111010010110110010101101011 '
b01100010111111110111100010110010 (
#1920
0$
#1930
1$
b11010010010010101101111000011101 &
b01111000111101111010100000011100 '
b01101111010010110110010101101011 (
#1940
0$
#1950
1$
b11101000010000110000110110000111 &
b11010010010010101101111000011101 '
b01111000111101111010100000011100 (
#1960
0$
#1970
1$
b01001011010000101000011000111001 &
b11101000010000110000110110000111 '
b11010010010010101101111000011101 (
#1980
0$
#1990
1$
b10111010100011011110101110100100 &
b01001011010000101000011000111001 '
b11101000010000110000110110000111 (
#2000
0$
#2010
1$
b00110011100001011001001111000000 &
b10111010100011011110101110100100 '
b01001011010000101000011000111001 (
#2020
0$
#2030
1$
b00000101110100000111000111011101 &
b00110011100001011001001111000000 '
b10111010100011011110101110100100 (
#2040
0$
#2050
1$
b11101110000100110111111101100100 &
b00000101110100000111000111011101 '
b00110011100001011001001111000000 (
#2060
0$
#2070
1$
b00111001010101100000010110011101 &
b11101110000100110111111101100100 '
b00000101110100000111000111011101 (
#2080
0$
#2090
1$
b11110011111000111111000101000001 &
b00111001010101100000010110011101 '
b11101110000100110111111101100100 (
#2100
0$
#2110
1$
b00100111011010011000010100000001 &
b11110011111000111111000101000001 '
b00111001010101100000010110011101 (
#2120
0$
#2130
1$
b00101101001110011111011011011110 &
b00100111011010011000010100000001 '
b11110011111000111111000101000001 (
#2140
0$
#2150
1$
b00011011010011010111011001000010 &
b00101101001110011111011011011110 '
b00100111011010011000010100000001 (
#2160
0$
#2170
1$
b01010100101000110111101111011111 &
b00011011010011010111011001000010 '
b00101101001110011111011011011110 (
#2180
0$
#2190
1$
b01001000100001110110110100100000 &
b01010100101000110111101111011111 '
b00011011010011010111011001000010 (
#2200
0$
#2210
1$
b01101111111100001111001000100001 &
b01001000100001110110110100100000 '
b01010100101000110111101111011111 (
#2220
0$
#2230
1$
b10011101001010101110100011111111 &
b01101111111100001111001000100001 '
b01001000100001110110110100100000 (
#2240
0$
#2250
1$
b10111000011110000101111101000001 &
b10011101001010101110100011111111 '
b01101111111100001111001000100001 (
#2260
0$
#2270
1$
b00001101000110111101101100100000 &
b10111000011110000101111101000001 '
b10011101001010101110100011111111 (
#2280
0$
#2290
1$
b01010101101000110100100001000000 &
b00001101000110111101101100100000 '
b10111000011110000101111101000001 (
#2300
0$
#2310
1$
b11000101100101000011101001100001 &
b01010101101000110100100001000000 '
b00001101000110111101101100100000 (
#2320
0$
#2330
1$
b01100010101111110010001101100000 &
b11000101100101000011101001100001 '
b01010101101000110100100001000000 (
#2340
0$
#2350
1$
b00011011001101111000001010100001 &
b01100010101111110010001101100000 '
b11000101100101000011101001100001 (
#2360
0$
#2370
1$
b00101000010100110101110111000001 &
b00011011001101111000001010100001 '
b01100010101111110010001101100000 (
#2380
0$
#2390
1$
b01111101111101101010011000000001 &
b00101000010100110101110111000001 '
b00011011001101111000001010100001 (
#2400
0$
#2410
1$
b01000011100010101110000001100010 &
b01111101111101101010011000000001 '
b00101000010100110101110111000001 (
#2420
0$
#2430
1$
b10100110010010100000001111000010 &
b01000011100010101110000001100010 '
b01111101111101101010011000000001 (
#2440
0$
#2450
1$
b11000001100000011000011001100011 &
b10100110010010100000001111000010 '
b01000011100010101110000001100010 (
#2460
0$
#2470
1$
b11101001110101001110010000100100 &
b11000001100000011000011001100011 '
b10100110010010100000001111000010 (
#2480
0$
#2490
1$
b01100111110010111000101000100101 &
b11101001110101001110010000100100 '
b11000001100000011000011001100011 (
#2500
0$
#2510
1$
b10101011010101100110101010000111 &
b01100111110010111000101000100101 '
b11101001110101001110010000100100 (
#2520
0$
#2530
1$
b01010001101000000110111001001001 &
b10101011010101100110101010000111 '
b01100111110010111000101000100101 (
#2540
0$
#2550
1$
b00010011001000011111010010101100 &
b01010001101000000110111001001001 '
b10101011010101100110101010000111 (
#2560
0$
#2570
1$
b11111100111101101101100011010000 &
b00010011001000011111010010101100 '
b01010001101000000110111001001001 (
#2580
0$
#2590
1$
b01100100110000100110001011110101 &
b11111100111101101101100011010000 '
b00010011001000011111010010101100 (
#2600
0$
#2610
1$
b00010000000110001100110101111100 &
b01100100110000100110001011110101 '
b11111100111101101101100011010000 (
#2620
0$
#2630
1$
b01100001101110010011101111000101 &
b00010000000110001100110101111100 '
b01100100110000100110001011110101 (
#2640
0$
#2650
1$
b01110100110110110011000001110001 &
b01100001101110010011101111000101 '
b00010000000110001100110101111100 (
#2660
0$
#2670
1$
b01110001110100100000100101000001 &
b01110100110110110011000001110001 '
b01100001101110010011101111000101 (
#2680
0$
#2690
1$
b11010110100101000110110000110110 &
b01110001110100100000100101000001 '
b01110100110110110011000001110001 (
#2700
0$
#2710
1$
b11100110101011010011100110110010 &
b11010110100101000110110000110110 '
b01110001110100100000100101000001 (
#2720
0$
#2730
1$
b01001000011001100111010101110111 &
b11100110101011010011100110110010 '
b11010110100101000110110000110110 (
#2740
0$
#2750
1$
b10111101010000011010010111101000 &
b01001000011001100111010101110111 '
b11100110101011010011100110110010 (
#2760
0$
#2770
1$
b00101111000100111010111100101001 &
b10111101010000011010010111101000 '
b01001000011001100111010101110111 (
#2780
0$
#2790
1$
b00000101101010000001101101011111 &
b00101111000100111010111100101001 '
b10111101010000011010010111101000 (
#2800
0$
#2810
1$
b11101100010101010101010100010001 &
b00000101101010000001101101011111 '
b00101111000100111010111100101001 (
#2820
0$
#2830
1$
b00110100101110111100101010001000 &
b11101100010101010101010100010001 '
b00000101101010000001101101011111 (
#2840
0$
#2850
1$
b11110001111111010111000001110000 &
b00110100101110111100101010001000 '
b11101100010101010101010100010001 (
#2860
0$
#2870
1$
b00100001000100010001111110011001 &
b11110001111111010111000001110000 '
b00110100101110111100101010001000 (
#2880
0$
#2890
1$
b00100110101110010011101011111000 &
b00100001000100010001111110011001 '
b11110001111111010111000001110000 (
#2900
0$
#2910
1$
b00010011000011101001000000001001 &
b00100110101110010011101011111000 '
b00100001000100010001111110011001 (
#2920
0$
#2930
1$
b01000111110010100101101010010001 &
b00010011000011101001000000001001 '
b00100110101110010011101011111000 (
#2940
0$
#2950
1$
b00111001110001111100101100000001 &
b01000111110010100101101010010001 '
b00010011000011101001000000001001 (
#2960
0$
#2970
1$
b01011010110110001110101010011010 &
b00111001110001111100101100000001 '
b01000111110010100101101010010001 (
#2980
0$
#2990
1$
b10000001100100100010010110010010 &
b01011010110110001110101010011010 '
b00111001110001111100101100000001 (
#3000
0$
#3010
1$
b10010100101000001011010110011011 &
b10000001100100100010010110010010 '
b01011010110110001110101010011010 (
#3020
0$
#3030
1$
b11011100011010110001000000101100 &
b10010100101000001011010110011011 '
b10000001100100100010010110010010 (
#3040
0$
#3050
1$
b00010110001100101101101100101101 &
b11011100011010110001000000101100 '
b10010100101000001011010110011011 (
#3060
0$
#3070
1$
b01110001000010111100010111000111 &
b00010110001100101101101100101101 '
b11011100011010110001000000101100 (
#3080
0$
#3090
1$
b11110010100111011110101101011001 &
b01110001000010111100010111000111 '
b00010110001100101101101100101101 (
#3100
0$
#3110
1$
b10000111001111101010000011110100 &
b11110010100111011110101101011001 '
b01110001000010111100010111000111 (
#3120
0$
#3130
1$
b01100011101010011011000100100000 &
b10000111001111101010000011110100 '
b11110010100111011110101101011001 (
#3140
0$
#3150
1$
b01111001110111001000110001001101 &
b01100011101010011011000100100000 '
b10000111001111101010000011110100 (
#3160
0$
#3170
1$
b11101010111010000101001000010100 &
b01111001110111001000110001001101 '
b01100011101010011011000100100000 (
#3180
0$
#3190
1$
b11011101100001100011110101101101 &
b11101010111010000101001000010100 '
b01111001110111001000110001001101 (
#3200
0$
#3210
1$
b01100100110001001101111001100001 &
b11011101100001100011110101101101 '
b11101010111010000101001000010100 (
#3220
0$
#3230
1$
b11001000011011101000111110000001 &
b01100100110001001101111001100001 '
b11011101100001100011110101101101 (
#3240
0$
#3250
1$
b01000010010010110001101111001110 &
b11001000011011101000111110000001 '
b01100100110001001101111001100001 (
#3260
0$
#3270
1$
b00101101001100110110110111100010 &
b01000010010010110001101111001110 '
b11001000011011101000111110000001 (
#3280
0$
#3290
1$
b00001010101110011010101101001111 &
b00101101001100110110110111100010 '
b01000010010010110001101111001110 (
#3300
0$
#3310
1$
b01101111011111101000100110110000 &
b00001010101110011010101101001111 '
b00101101001100110110110111100010 (
#3320
0$
#3330
1$
b00110111111011010001100100110001 &
b01101111011111101000100110110000 '
b00001010101110011010101101001111 (
#3340
0$
#3350
1$
b01111010001110000011010011111111 &
b00110111111011010001100100110001 '
b01101111011111101000100110110000 (
#3360
0$
#3370
1$
b10100111011010111010001011100001 &
b01111010001110000011010011111111 '
b00110111111011010001100100110001 (
#3380
0$
#3390
1$
b10110010001001010100111000110000 &
b10100111011010111010001011100001 '
b01111010001110000011010011111111 (
#3400
0$
#3410
1$
b00100001101000111101011111100000 &
b10110010001001010100111000110000 '
b10100111011010111010001011100001 (
#3420
0$
#3430
1$
b01011001100100001111000100010001 &
b00100001101000111101011111100000 '
b10110010001001010100111000110000 (
#3440
0$
#3450
1$
b11010011110010010010011000010000 &
b01011001100100001111000100010001 '
b00100001101000111101011111100000 (
#3460
0$
#3470
1$
b01111011001101001100100011110001 &
b11010011110010010010011000010000 '
b01011001100100001111000100010001 (
#3480
0$
#3490
1$
b00101101010110100001011100100001 &
b01111011001101001100100011110001 '
b11010011110010010010011000010000 (
#3500
0$
#3510
1$
b01001110111111011110111100000001 &
b00101101010110100001011100100001 '
b01111011001101001100100011110001 (
#3520
0$
#3530
1$
b10101000100011101110000000010010 &
b01001110111111011110111100000001 '
b00101101010110100001011100100001 (
#3540
0$
#3550
1$
b01111100010110000000011000100010 &
b10101000100011101110000000010010 '
b01001110111111011110111100000001 (
#3560
0$
#3570
1$
b11110111100011001100111100010011 &
b01111100010110000000011000100010 '
b10101000100011101110000000010010 (
#3580
0$
#3590
1$
b00100100111001101110011000110100 &
b11110111100011001100111100010011 '
b01111100010110000000011000100010 (
#3600
0$
#3610
1$
b01110011111001001101010100110101 &
b00100100111001101110011000110100 '
b11110111100011001100111100010011 (
#3620
0$
#3630
1$
b00011100011100111011010101000111 &
b01110011111001001101010100110101 '
b00100100111001101110011000110100 (
#3640
0$
#3650
1$
b10011000110010111011101101101001 &
b00011100011100111011010101000111 '
b01110011111001001101010100110101 (
#3660
0$
#3670
1$
b10010000010110001000101001111100 &
b10011000110010111011101101101001 '
b00011100011100111011010101000111 (
#3680
0$
#3690
1$
b10110101001111110111000010110000 &
b10010000010110001000101001111100 '
b10011000110010111011101101101001 (
#3700
0$
#3710
1$
b00101001001001000100010111100101 &
b10110101001111110111000010110000 '
b10010000010110001000101001111100 (
#3720
0$
#3730
1$
b01000101100101111111101100101100 &
b00101001001001000100010111100101 '
b10110101001111110111000010110000 (
#3740
0$
#3750
1$
b11011110011000111011011010010101 &
b01000101100101111111101100101100 '
b00101001001001000100010111100101 (
#3760
0$
#3770
1$
b01101110101111000100000100010001 &
b11011110011000111011011010010101 '
b01000101100101111111101100101100 (
#3780
0$
#3790
1$
b00100011111110111011000111000001 &
b01101110101111000100000100010001 '
b11011110011000111011011010010101 (
#3800
0$
#3810
1$
b01001101000111111111011110100110 &
b00100011111110111011000111000001 '
b01101110101111000100000100010001 (
#3820
0$
#3830
1$
b10010010101101111111001011010010 &
b01001101000111111111011110100110 '
b00100011111110111011000111000001 (
#3840
0$
#3850
1$
b01110001000110111010100101100111 &
b10010010101101111111001011010010 '
b01001101000111111111011110100110 (
#3860
0$
#3870
1$
b11011111110101111110101001111000 &
b01110001000110111010100101100111 '
b10010010101101111111001011010010 (
#3880
0$
#3890
1$
b00000011110100111001110000111001 &
b11011111110101111110101001111000 '
b01110001000110111010100101100111 (
#3900
0$
#3910
1$
b01010000111100111001001111011111 &
b00000011110100111001110000111001 '
b11011111110101111110101001111000 (
#3920
0$
#3930
1$
b11100011101010111000011010110001 &
b01010000111100111001001111011111 '
b00000011110100111001110000111001 (
#3940
0$
#3950
1$
b01010100110001110011000000011000 &
b11100011101010111000011010110001 '
b01010000111100111001001111011111 (
#3960
0$
#3970
1$
b00110100100111110001101010010000 &
b01010100110001110011000000011000 '
b11100011101010111000011010110001 (
#3980
0$
#3990
1$
b00111000011100101011011011001001 &
b00110100100111110001101010010000 '
b01010100110001110011000000011000 (
#4000
0$
#4010
1$
b10001001011001100100101010101000 &
b00111000011100101011011011001001 '
b00110100100111110001101010010000 (
#4020
0$
#4030
1$
b01101101000100011101000101011001 &
b10001001011001100100101010101000 '
b00111000011100101011011011001001 (
#4040
0$
#4050
1$
b11000001110110010000000101110001 &
b01101101000100011101000101011001 '
b10001001011001100100101010101000 (
#4060
0$
#4070
1$
b11110110011110000001110000000001 &
b11000001110110010000000101110001 '
b01101101000100011101000101011001 (
#4080
0$
#4090
1$
b00101110111010101101001011001010 &
b11110110011110000001110000000001 '
b11000001110110010000000101110001 (
#4100
0$
#4110
1$
b10111000010100010001110101110010 &
b00101110111010101101001011001010 '
b11110110011110000001110000000001 (
#4120
0$
#4130
1$
b00100101011000101110111011001011 &
b10111000010100010001110101110010 '
b00101110111010101101001011001010 (
#4140
0$
#4150
1$
b11100111001110111111000000111100 &
b00100101011000101110111011001011 '
b10111000010100010001110101110010 (
#4160
0$
#4170
1$
b11011101101101000000110000111101 &
b11100111001110111111000000111100 '
b00100101011000101110111011001011 (
#4180
0$
#4190
1$
b00001100100111101101111100000111 &
b11011101101101000000110000111101 '
b11100111001110111111000000111100 (
#4200
0$
#4210
1$
b11000100111011111111110001111001 &
b00001100100111101101111100000111 '
b11011101101101000000110000111101 (
#4220
0$
#4230
1$
b11101010010100101110101101000100 &
b11000100111011111111110001111001 '
b00001100100111101101111100000111 (
#4240
0$
#4250
1$
b11010001100011101101101110000000 &
b11101010010100101110101101000100 '
b11000100111011111111110001111001 (
#4260
0$
#4270
1$
b10101111010000101110011110111101 &
b11010001100011101101101110000000 '
b11101010010100101110101101000100 (
#4280
0$
#4290
1$
b10111011111000011100011011000100 &
b10101111010000101110011110111101 '
b11010001100011101101101110000000 (
#4300
0$
#4310
1$
b10000000110100011100001100111101 &
b10111011111000011100011011000100 '
b10101111010000101110011110111101 (
#4320
0$
#4330
1$
b01101011001001001010111010000001 &
b10000000110100011100001100111101 '
b10111011111000011100011011000100 (
#4340
0$
#4350
1$
b00111100101100111000101000000001 &
b01101011001001001010111010000001 '
b10000000110100011100001100111101 (
#4360
0$
#4370
1$
b11101011111101100111000110111110 &
b00111100101100111000101000000001 '
b01101011001001001010111010000001 (
#4380
0$
#4390
1$
b10100111110110000011100010000010 &
b11101011111101100111000110111110 '
b00111100101100111000101000000001 (
#4400
0$
#4410
1$
b00101000101010011111101110111111 &
b10100111110110000011100010000010 '
b11101011111101100111000110111110 (
#4420
0$
#4430
1$
b10010011110011101010101001000000 &
b00101000101010011111101110111111 '
b10100111110110000011100010000010 (
#4440
0$
#4450
1$
b11010000100000100011010001000001 &
b10010011110011101010101001000000 '
b00101000101010011111101110111111 (
#4460
0$
#4470
1$
b10111100011110001010010111111111 &
b11010000100000100011010001000001 '
b10010011110011101010101001000000 (
#4480
0$
#4490
1$
b01100100010100001101111010000001 &
b10111100011110001010010111111111 '
b11010000100000100011010001000001 (
#4500
0$
#4510
1$
b10001100111110101101101001000000 &
b01100100010100001101111010000001 '
b10111100011110001010010111111111 (
#4520
0$
#4530
1$
b00100000110010011000010010000000 &
b10001100111110101101101001000000 '
b01100100010100001101111010000001 (
#4540
0$
#4550
1$
b11110001010010111011100011000001 &
b00100000110010011000010010000000 '
b10001100111110101101101001000000 (
#4560
0$
#4570
1$
b10101101110001000101111011000000 &
b11110001010010111011100011000001 '
b00100000110010011000010010000000 (
#4580
0$
#4590
1$
b00010010000101010011110101000001 &
b10101101110001000101111011000000 '
b11110001010010111011100011000001 (
#4600
0$
#4610
1$
b10011111000100000001011110000001 &
b00010010000101010011110101000001 '
b10101101110001000101111011000000 (
#4620
0$
#4630
1$
b10111111110110011001110000000001 &
b10011111000100000001011110000001 '
b00010010000101010011110101000001 (
#4640
0$
#4650
1$
b10110001001001010101010011000010 &
b10111111110110011001110000000001 '
b10011111000100000001011110000001 (
#4660
0$
#4670
1$
b01011110111010011011001110000010 &
b10110001001001010101010011000010 '
b10111111110110011001110000000001 (
#4680
0$
#4690
1$
b01110000111111101111000011000011 &
b01011110111010011011001110000010 '
b10110001001001010101010011000010 (
#4700
0$
#4710
1$
b00010000000011110000100001000100 &
b01110000111111101111000011000011 '
b01011110111010011011001110000010 (
#4720
0$
#4730
1$
b11001111111010001010010001000101 &
b00010000000011110000100001000100 '
b01110000111111101111000011000011 (
#4740
0$
#4750
1$
b10000001000011011111100100000111 &
b11001111111010001010010001000101 '
b00010000000011110000100001000100 (
#4760
0$
#4770
1$
b11011111111101111010110010001001 &
b10000001000011011111100100000111 '
b11001111111010001010010001000101 (
#4780
0$
#4790
1$
b01010000111101101001110101001100 &
b11011111111101111010110010001001 '
b10000001000011011111100100000111 (
#4800
0$
#4810
1$
b01100001000001011010010110010000 &
b01010000111101101001110101001100 '
b11011111111101111010110010001001 (
#4820
0$
#4830
1$
b00110000111011100100100111010101 &
b01100001000001011010010110010000 '
b01010000111101101001110101001100 (
#4840
0$
#4850
1$
b10110001111111000100001011011100 &
b00110000111011100100100111010101 '
b01100001000001011010010110010000 (
#4860
0$
#4870
1$
b10010001111100111110111101100101 &
b10110001111111000100001011011100 '
b00110000111011100100100111010101 (
#4880
0$
#4890
1$
b11100010111010101000110010110001 &
b10010001111100111110111101100101 '
b10110001111111000100001011011100 (
#4900
0$
#4910
1$
b01000011111100000011001001000001 &
b11100010111010101000110010110001 '
b10010001111100111110111101100101 (
#4920
0$
#4930
1$
b01110100110111100111110000010110 &
b01000011111100000011001001000001 '
b11100010111010101000110010110001 (
#4940
0$
#4950
1$
b00100110110110101011111011110010 &
b01110100110111100111110000010110 '
b01000011111100000011001001000001 (
#4960
0$
#4970
1$
b10111000110011101010111001010111 &
b00100110110110101011111011110010 '
b01110100110111100111110000010110 (
#4980
0$
#4990
1$
b10011011101110010011101100001000 &
b10111000110011101010111001010111 '
b00100110110110101011111011110010 (
#5000
0$
#5010
1$
b11011111101010010110110101001001 &
b10011011101110010011101100001000 '
b10111000110011101010111001010111 (
#5020
0$
