week4/lab8/fibonacci_generator.v
module fibonacci_generator(
    input rst,
    input clk,
    input enable,
    output reg [31:0] fib_out
);

    reg [31:0] fib_prev1;
    reg [31:0] fib_prev2;

    always @(posedge clk or posedge rst) begin 
        if (rst) begin
            fib_prev1 <= 32'b1;
            fib_prev2 <= 32'b0;
            fib_out <= 32'b0;
        end else if (enable) begin
            fib_out <= fib_prev1 + fib_prev2;
            fib_prev2 <= fib_prev1;
            fib_prev1 <= fib_prev1 + fib_prev2;
        end
    end

endmodule

week4/lab8/fibonacci_generator.vcd
$version Generated by VerilatedVcd $end
$timescale 1ps $end
 $scope module TOP $end
  $var wire 1 # rst $end
  $var wire 1 $ clk $end
  $var wire 1 % enable $end
  $var wire 32 & fib_out [31:0] $end
  $scope module fibonacci_generator $end
   $var wire 1 # rst $end
   $var wire 1 $ clk $end
   $var wire 1 % enable $end
   $var wire 32 & fib_out [31:0] $end
   $var wire 32 ' fib_prev1 [31:0] $end
   $var wire 32 ( fib_prev2 [31:0] $end
  $upscope $end
 $upscope $end
$enddefinitions $end


#0
1#
0$
0%
b00000000000000000000000000000000 &
b00000000000000000000000000000000 '
b00000000000000000000000000000000 (
#1
1$
1%
b00000000000000000000000000000001 '
#2
0$
#3
1$
#4
0$
#5
1$
#6
0$
#7
1$
#8
0$
#9
1$
#10
0#
0$
#11
1$
b00000000000000000000000000000001 &
b00000000000000000000000000000001 (
#12
0$
#13
1$
b00000000000000000000000000000010 &
b00000000000000000000000000000010 '
#14
0$
#15
1$
b00000000000000000000000000000011 &
b00000000000000000000000000000011 '
b00000000000000000000000000000010 (
#16
0$
#17
1$
b00000000000000000000000000000101 &
b00000000000000000000000000000101 '
b00000000000000000000000000000011 (
#18
0$
#19
1$
b00000000000000000000000000001000 &
b00000000000000000000000000001000 '
b00000000000000000000000000000101 (
#20
0$
#21
1$
b00000000000000000000000000001101 &
b00000000000000000000000000001101 '
b00000000000000000000000000001000 (
#22
0$
#23
1$
b00000000000000000000000000010101 &
b00000000000000000000000000010101 '
b00000000000000000000000000001101 (
#24
0$
#25
1$
b00000000000000000000000000100010 &
b00000000000000000000000000100010 '
b00000000000000000000000000010101 (
#26
0$
#27
1$
b00000000000000000000000000110111 &
b00000000000000000000000000110111 '
b00000000000000000000000000100010 (
#28
0$
#29
1$
b00000000000000000000000001011001 &
b00000000000000000000000001011001 '
b00000000000000000000000000110111 (
#30
0$
#31
1$
b00000000000000000000000010010000 &
b00000000000000000000000010010000 '
b00000000000000000000000001011001 (
#32
0$
#33
1$
b00000000000000000000000011101001 &
b00000000000000000000000011101001 '
b00000000000000000000000010010000 (
#34
0$
#35
1$
b00000000000000000000000101111001 &
b00000000000000000000000101111001 '
b00000000000000000000000011101001 (
#36
0$
#37
1$
b00000000000000000000001001100010 &
b00000000000000000000001001100010 '
b00000000000000000000000101111001 (
#38
0$
#39
1$
b00000000000000000000001111011011 &
b00000000000000000000001111011011 '
b00000000000000000000001001100010 (
#40
0$
#41
1$
b00000000000000000000011000111101 &
b00000000000000000000011000111101 '
b00000000000000000000001111011011 (
#42
0$
#43
1$
b00000000000000000000101000011000 &
b00000000000000000000101000011000 '
b00000000000000000000011000111101 (
#44
0$
#45
1$
b00000000000000000001000001010101 &
b00000000000000000001000001010101 '
b00000000000000000000101000011000 (
#46
0$
#47
1$
b00000000000000000001101001101101 &
b00000000000000000001101001101101 '
b00000000000000000001000001010101 (
#48
0$
#49
1$
b00000000000000000010101011000010 &
b00000000000000000010101011000010 '
b00000000000000000001101001101101 (
#50
0$
#51
1$
b00000000000000000100010100101111 &
b00000000000000000100010100101111 '
b00000000000000000010101011000010 (
#52
0$
#53
1$
b00000000000000000110111111110001 &
b00000000000000000110111111110001 '
b00000000000000000100010100101111 (
#54
0$
#55
1$
b00000000000000001011010100100000 &
b00000000000000001011010100100000 '
b00000000000000000110111111110001 (
#56
0$
#57
1$
b00000000000000010010010100010001 &
b00000000000000010010010100010001 '
b00000000000000001011010100100000 (
#58
0$
#59
1$
b00000000000000011101101000110001 &
b00000000000000011101101000110001 '
b00000000000000010010010100010001 (
#60
0$
#61
1$
b00000000000000101111111101000010 &
b00000000000000101111111101000010 '
b00000000000000011101101000110001 (
#62
0$
#63
1$
b00000000000001001101100101110011 &
b00000000000001001101100101110011 '
b00000000000000101111111101000010 (
#64
0$
#65
1$
b00000000000001111101100010110101 &
b00000000000001111101100010110101 '
b00000000000001001101100101110011 (
#66
0$
#67
1$
b00000000000011001011001000101000 &
b00000000000011001011001000101000 '
b00000000000001111101100010110101 (
#68
0$
#69
1$
b00000000000101001000101011011101 &
b00000000000101001000101011011101 '
b00000000000011001011001000101000 (
#70
0$
#71
1$
b00000000001000010011110100000101 &
b00000000001000010011110100000101 '
b00000000000101001000101011011101 (
#72
0$
#73
1$
b00000000001101011100011111100010 &
b00000000001101011100011111100010 '
b00000000001000010011110100000101 (
#74
0$
#75
1$
b00000000010101110000010011100111 &
b00000000010101110000010011100111 '
b00000000001101011100011111100010 (
#76
0$
#77
1$
b00000000100011001100110011001001 &
b00000000100011001100110011001001 '
b00000000010101110000010011100111 (
#78
0$
#79
1$
b00000000111000111101000110110000 &
b00000000111000111101000110110000 '
b00000000100011001100110011001001 (
#80
0$
#81
1$
b00000001011100001001111001111001 &
b00000001011100001001111001111001 '
b00000000111000111101000110110000 (
#82
0$
#83
1$
b00000010010101000111000000101001 &
b00000010010101000111000000101001 '
b00000001011100001001111001111001 (
#84
0$
#85
1$
b00000011110001010000111010100010 &
b00000011110001010000111010100010 '
b00000010010101000111000000101001 (
#86
0$
#87
1$
b00000110000110010111111011001011 &
b00000110000110010111111011001011 '
b00000011110001010000111010100010 (
#88
0$
#89
1$
b00001001110111101000110101101101 &
b00001001110111101000110101101101 '
b00000110000110010111111011001011 (
#90
0$
#91
1$
b00001111111110000000110000111000 &
b00001111111110000000110000111000 '
b00001001110111101000110101101101 (
#92
0$
#93
1$
b00011001110101101001100110100101 &
b00011001110101101001100110100101 '
b00001111111110000000110000111000 (
#94
0$
#95
1$
b00101001110011101010010111011101 &
b00101001110011101010010111011101 '
b00011001110101101001100110100101 (
#96
0$
#97
1$
b01000011101001010011111110000010 &
b01000011101001010011111110000010 '
b00101001110011101010010111011101 (
#98
0$
#99
1$
b01101101011100111110010101011111 &
b01101101011100111110010101011111 '
b01000011101001010011111110000010 (
#100
0$
#101
1$
b10110001000110010010010011100001 &
b10110001000110010010010011100001 '
b01101101011100111110010101011111 (
#102
0$
#103
1$
b00011110100011010000101001000000 &
b00011110100011010000101001000000 '
b10110001000110010010010011100001 (
#104
0$
#105
1$
b11001111101001100010111100100001 &
b11001111101001100010111100100001 '
b00011110100011010000101001000000 (
#106
0$
#107
1$
b11101110001100110011100101100001 &
b11101110001100110011100101100001 '
b11001111101001100010111100100001 (
#108
0$
#109
1$
b10111101110110010110100010000010 &
b10111101110110010110100010000010 '
b11101110001100110011100101100001 (
#110
0$
#111
1$
b10101100000011001010000111100011 &
b10101100000011001010000111100011 '
b10111101110110010110100010000010 (
#112
0$
#113
1$
b01101001111001100000101001100101 &
b01101001111001100000101001100101 '
b10101100000011001010000111100011 (
#114
0$
#115
1$
b00010101111100101010110001001000 &
b00010101111100101010110001001000 '
b01101001111001100000101001100101 (
#116
0$
#117
1$
b01111111110110001011011010101101 &
b01111111110110001011011010101101 '
b00010101111100101010110001001000 (
#118
0$
#119
1$
b10010101110010110110001011110101 &
b10010101110010110110001011110101 '
b01111111110110001011011010101101 (
#120
0$
#121
1$
b00010101101001000001100110100010 &
b00010101101001000001100110100010 '
b10010101110010110110001011110101 (
#122
0$
#123
1$
b10101011011011110111110010010111 &
b10101011011011110111110010010111 '
b00010101101001000001100110100010 (
#124
0$
#125
1$
b11000001000100111001011000111001 &
b11000001000100111001011000111001 '
b10101011011011110111110010010111 (
#126
0$
#127
1$
b01101100100000110001001011010000 &
b01101100100000110001001011010000 '
b11000001000100111001011000111001 (
#128
0$
#129
1$
b00101101100101101010100100001001 &
b00101101100101101010100100001001 '
b01101100100000110001001011010000 (
#130
0$
#131
1$
b10011010000110011011101111011001 &
b10011010000110011011101111011001 '
b00101101100101101010100100001001 (
#132
0$
#133
1$
b11000111101100000110010011100010 &
b11000111101100000110010011100010 '
b10011010000110011011101111011001 (
#134
0$
#135
1$
b01100001110010100010000010111011 &
b01100001110010100010000010111011 '
b11000111101100000110010011100010 (
#136
0$
#137
1$
b00101001011110101000010110011101 &
b00101001011110101000010110011101 '
b01100001110010100010000010111011 (
#138
0$
#139
1$
b10001011010001001010011001011000 &
b10001011010001001010011001011000 '
b00101001011110101000010110011101 (
#140
0$
#141
1$
b10110100101111110010101111110101 &
b10110100101111110010101111110101 '
b10001011010001001010011001011000 (
#142
0$
#143
1$
b01000000000000111101001001001101 &
b01000000000000111101001001001101 '
b10110100101111110010101111110101 (
#144
0$
#145
1$
b11110100110000101111111001000010 &
b11110100110000101111111001000010 '
b01000000000000111101001001001101 (
#146
0$
#147
1$
b00110100110001101101000010001111 &
b00110100110001101101000010001111 '
b11110100110000101111111001000010 (
#148
0$
#149
1$
b00101001100010011100111011010001 &
b00101001100010011100111011010001 '
b00110100110001101101000010001111 (
#150
0$
#151
1$
b01011110010100001001111101100000 &
b01011110010100001001111101100000 '
b00101001100010011100111011010001 (
#152
0$
#153
1$
b10000111110110100110111000110001 &
b10000111110110100110111000110001 '
b01011110010100001001111101100000 (
#154
0$
#155
1$
b11100110001010110000110110010001 &
b11100110001010110000110110010001 '
b10000111110110100110111000110001 (
#156
0$
#157
1$
b01101110000001010111101111000010 &
b01101110000001010111101111000010 '
b11100110001010110000110110010001 (
#158
0$
#159
1$
b01010100001100001000100101010011 &
b01010100001100001000100101010011 '
b01101110000001010111101111000010 (
#160
0$
#161
1$
b11000010001101100000010100010101 &
b11000010001101100000010100010101 '
b01010100001100001000100101010011 (
#162
0$
#163
1$
b00010110011001101000111001101000 &
b00010110011001101000111001101000 '
b11000010001101100000010100010101 (
#164
0$
#165
1$
b11011000100111001001001101111101 &
b11011000100111001001001101111101 '
b00010110011001101000111001101000 (
#166
0$
#167
1$
b11101111000000110010000111100101 &
b11101111000000110010000111100101 '
b11011000100111001001001101111101 (
#168
0$
#169
1$
b11000111100111111011010101100010 &
b11000111100111111011010101100010 '
b11101111000000110010000111100101 (
#170
0$
#171
1$
b10110110101000101101011101000111 &
b10110110101000101101011101000111 '
b11000111100111111011010101100010 (
#172
0$
#173
1$
b01111110010000101000110010101001 &
b01111110010000101000110010101001 '
b10110110101000101101011101000111 (
#174
0$
#175
1$
b00110100111001010110001111110000 &
b00110100111001010110001111110000 '
b01111110010000101000110010101001 (
#176
0$
#177
1$
b10110011001001111111000010011001 &
b10110011001001111111000010011001 '
b00110100111001010110001111110000 (
#178
0$
#179
1$
b11101000000011010101010010001001 &
b11101000000011010101010010001001 '
b10110011001001111111000010011001 (
#180
0$
#181
1$
b10011011001101010100010100100010 &
b10011011001101010100010100100010 '
b11101000000011010101010010001001 (
#182
0$
#183
1$
b10000011010000101001100110101011 &
b10000011010000101001100110101011 '
b10011011001101010100010100100010 (
#184
0$
#185
1$
b00011110011101111101111011001101 &
b00011110011101111101111011001101 '
b10000011010000101001100110101011 (
#186
0$
#187
1$
b10100001101110100111100001111000 &
b10100001101110100111100001111000 '
b00011110011101111101111011001101 (
#188
0$
#189
1$
b11000000001100100101011101000101 &
b11000000001100100101011101000101 '
b10100001101110100111100001111000 (
#190
0$
#191
1$
b01100001111011001100111110111101 &
b01100001111011001100111110111101 '
b11000000001100100101011101000101 (
#192
0$
#193
1$
b00100010000111110010011100000010 &
b00100010000111110010011100000010 '
b01100001111011001100111110111101 (
#194
0$
#195
1$
b10000100000010111111011010111111 &
b10000100000010111111011010111111 '
b00100010000111110010011100000010 (
#196
0$
#197
1$
b10100110001010110001110111000001 &
b10100110001010110001110111000001 '
b10000100000010111111011010111111 (
#198
0$
#199
1$
b00101010001101110001010010000000 &
b00101010001101110001010010000000 '
b10100110001010110001110111000001 (
#200
0$
#201
1$
b11010000011000100011001001000001 &
b11010000011000100011001001000001 '
b00101010001101110001010010000000 (
#202
0$
#203
1$
b11111010100110010100011011000001 &
b11111010100110010100011011000001 '
b11010000011000100011001001000001 (
#204
0$
#205
1$
b11001010111110110111100100000010 &
b11001010111110110111100100000010 '
b11111010100110010100011011000001 (
#206
0$
#207
1$
b11000101100101001011111111000011 &
b11000101100101001011111111000011 '
b11001010111110110111100100000010 (
#208
0$
#209
1$
b10010000100100000011100011000101 &
b10010000100100000011100011000101 '
b11000101100101001011111111000011 (
#210
0$
#211
1$
b01010110001001001111100010001000 &
b01010110001001001111100010001000 '
b10010000100100000011100011000101 (
#212
0$
#213
1$
b11100110101101010011000101001101 &
b11100110101101010011000101001101 '
b01010110001001001111100010001000 (
#214
0$
#215
1$
b00111100110110100010100111010101 &
b00111100110110100010100111010101 '
b11100110101101010011000101001101 (
#216
0$
#217
1$
b00100011100011110101101100100010 &
b00100011100011110101101100100010 '
b00111100110110100010100111010101 (
#218
0$
#219
1$
b01100000011010011000010011110111 &
b01100000011010011000010011110111 '
b00100011100011110101101100100010 (
#220
0$
#221
1$
b10000011111110001110000000011001 &
b10000011111110001110000000011001 '
b01100000011010011000010011110111 (
#222
0$
#223
1$
b11100100011000100110010100010000 &
b11100100011000100110010100010000 '
b10000011111110001110000000011001 (
#224
0$
#225
1$
b01101000010110110100010100101001 &
b01101000010110110100010100101001 '
b11100100011000100110010100010000 (
#226
0$
#227
1$
b01001100101111011010101000111001 &
b01001100101111011010101000111001 '
b01101000010110110100010100101001 (
#228
0$
#229
1$
b10110101000110001110111101100010 &
b10110101000110001110111101100010 '
b01001100101111011010101000111001 (
#230
0$
#231
1$
b00000001110101101001100110011011 &
b00000001110101101001100110011011 '
b10110101000110001110111101100010 (
#232
0$
#233
1$
b10110110111011111000100011111101 &
b10110110111011111000100011111101 '
b00000001110101101001100110011011 (
#234
0$
#235
1$
b10111000110001100010001010011000 &
b10111000110001100010001010011000 '
b10110110111011111000100011111101 (
#236
0$
#237
1$
b01101111101101011010101110010101 &
b01101111101101011010101110010101 '
b10111000110001100010001010011000 (
#238
0$
#239
1$
b00101000011110111100111000101101 &
b00101000011110111100111000101101 '
b01101111101101011010101110010101 (
#240
0$
#241
1$
b10011000001100010111100111000010 &
b10011000001100010111100111000010 '
b00101000011110111100111000101101 (
#242
0$
#243
1$
b11000000101011010100011111101111 &
b11000000101011010100011111101111 '
b10011000001100010111100111000010 (
#244
0$
#245
1$
b01011000110111101100000110110001 &
b01011000110111101100000110110001 '
b11000000101011010100011111101111 (
#246
0$
#247
1$
b00011001100011000000100110100000 &
b00011001100011000000100110100000 '
b01011000110111101100000110110001 (
#248
0$
#249
1$
b01110010011010101100101101010001 &
b01110010011010101100101101010001 '
b00011001100011000000100110100000 (
#250
0$
#251
1$
b10001011111101101101010011110001 &
b10001011111101101101010011110001 '
b01110010011010101100101101010001 (
#252
0$
#253
1$
b11111110011000011010000001000010 &
b11111110011000011010000001000010 '
b10001011111101101101010011110001 (
#254
0$
#255
1$
b10001010010110000111010100110011 &
b10001010010110000111010100110011 '
b11111110011000011010000001000010 (
#256
0$
#257
1$
b10001000101110100001010101110101 &
b10001000101110100001010101110101 '
b10001010010110000111010100110011 (
#258
0$
#259
1$
b00010011000100101000101010101000 &
b00010011000100101000101010101000 '
b10001000101110100001010101110101 (
#260
0$
#261
1$
b10011011110011001010000000011101 &
b10011011110011001010000000011101 '
b00010011000100101000101010101000 (
#262
0$
#263
1$
b10101110110111110010101011000101 &
b10101110110111110010101011000101 '
b10011011110011001010000000011101 (
#264
0$
#265
1$
b01001010101010111100101011100010 &
b01001010101010111100101011100010 '
b10101110110111110010101011000101 (
#266
0$
#267
1$
b11111001100010101111010110100111 &
b11111001100010101111010110100111 '
b01001010101010111100101011100010 (
#268
0$
#269
1$
b01000100001101101100000010001001 &
b01000100001101101100000010001001 '
b11111001100010101111010110100111 (
#270
0$
#271
1$
b00111101110000011011011000110000 &
b00111101110000011011011000110000 '
b01000100001101101100000010001001 (
#272
0$
#273
1$
b10000001111110000111011010111001 &
b10000001111110000111011010111001 '
b00111101110000011011011000110000 (
#274
0$
#275
1$
b10111111101110100010110011101001 &
b10111111101110100010110011101001 '
b10000001111110000111011010111001 (
#276
0$
#277
1$
b01000001101100101010001110100010 &
b01000001101100101010001110100010 '
b10111111101110100010110011101001 (
#278
0$
#279
1$
b00000001011011001101000010001011 &
b00000001011011001101000010001011 '
b01000001101100101010001110100010 (
#280
0$
#281
1$
b01000011000111110111010000101101 &
b01000011000111110111010000101101 '
b00000001011011001101000010001011 (
#282
0$
#283
1$
b01000100100011000100010010111000 &
b01000100100011000100010010111000 '
b01000011000111110111010000101101 (
#284
0$
#285
1$
b10000111101010111011100011100101 &
b10000111101010111011100011100101 '
b01000100100011000100010010111000 (
#286
0$
#287
1$
b11001100001101111111110110011101 &
b11001100001101111111110110011101 '
b10000111101010111011100011100101 (
#288
0$
#289
1$
b01010011111000111011011010000010 &
b01010011111000111011011010000010 '
b11001100001101111111110110011101 (
#290
0$
#291
1$
b00100000000110111011010000011111 &
b00100000000110111011010000011111 '
b01010011111000111011011010000010 (
#292
0$
#293
1$
b01110011111111110110101010100001 &
b01110011111111110110101010100001 '
b00100000000110111011010000011111 (
#294
0$
#295
1$
b10010100000110110001111011000000 &
b10010100000110110001111011000000 '
b01110011111111110110101010100001 (
#296
0$
#297
1$
b00001000000110101000100101100001 &
b00001000000110101000100101100001 '
b10010100000110110001111011000000 (
#298
0$
#299
1$
b10011100001101011010100000100001 &
b10011100001101011010100000100001 '
b00001000000110101000100101100001 (
#300
0$
#301
1$
b10100100010100000011000110000010 &
b10100100010100000011000110000010 '
b10011100001101011010100000100001 (
#302
0$
#303
1$
b01000000100001011101100110100011 &
b01000000100001011101100110100011 '
b10100100010100000011000110000010 (
#304
0$
#305
1$
b11100100110101100000101100100101 &
b11100100110101100000101100100101 '
b01000000100001011101100110100011 (
#306
0$
#307
1$
b00100101010110111110010011001000 &
b00100101010110111110010011001000 '
b11100100110101100000101100100101 (
#308
0$
#309
1$
b00001010001100011110111111101101 &
b00001010001100011110111111101101 '
b00100101010110111110010011001000 (
#310
0$
#311
1$
b00101111100011011101010010110101 &
b00101111100011011101010010110101 '
b00001010001100011110111111101101 (
#312
0$
#313
1$
b00111001101111111100010010100010 &
b00111001101111111100010010100010 '
b00101111100011011101010010110101 (
#314
0$
#315
1$
b01101001010011011001100101010111 &
b01101001010011011001100101010111 '
b00111001101111111100010010100010 (
#316
0$
#317
1$
b10100011000011010101110111111001 &
b10100011000011010101110111111001 '
b01101001010011011001100101010111 (
#318
0$
#319
1$
b00001100010110101111011101010000 &
b00001100010110101111011101010000 '
b10100011000011010101110111111001 (
#320
0$
#321
1$
b10101111011010000101010101001001 &
b10101111011010000101010101001001 '
b00001100010110101111011101010000 (
#322
0$
#323
1$
b10111011110000110100110010011001 &
b10111011110000110100110010011001 '
b10101111011010000101010101001001 (
#324
0$
#325
1$
b01101011001010111010000111100010 &
b01101011001010111010000111100010 '
b10111011110000110100110010011001 (
#326
0$
#327
1$
b00100110111011101110111001111011 &
b00100110111011101110111001111011 '
b01101011001010111010000111100010 (
#328
0$
#329
1$
b10010010000110101001000001011101 &
b10010010000110101001000001011101 '
b00100110111011101110111001111011 (
#330
0$
#331
1$
b10111001000010010111111011011000 &
b10111001000010010111111011011000 '
b10010010000110101001000001011101 (
#332
0$
#333
1$
b01001011001001000000111100110101 &
b01001011001001000000111100110101 '
b10111001000010010111111011011000 (
#334
0$
#335
1$
b00000100001011011000111000001101 &
b00000100001011011000111000001101 '
b01001011001001000000111100110101 (
#336
0$
#337
1$
b01001111010100011001110101000010 &
b01001111010100011001110101000010 '
b00000100001011011000111000001101 (
#338
0$
#339
1$
b01010011011111110010101101001111 &
b01010011011111110010101101001111 '
b01001111010100011001110101000010 (
#340
0$
#341
1$
b10100010110100001100100010010001 &
b10100010110100001100100010010001 '
b01010011011111110010101101001111 (
#342
0$
#343
1$
b11110110010011111111001111100000 &
b11110110010011111111001111100000 '
b10100010110100001100100010010001 (
#344
0$
#345
1$
b10011001001000001011110001110001 &
b10011001001000001011110001110001 '
b11110110010011111111001111100000 (
#346
0$
#347
1$
b10001111011100001011000001010001 &
b10001111011100001011000001010001 '
b10011001001000001011110001110001 (
#348
0$
#349
1$
b00101000100100010110110011000010 &
b00101000100100010110110011000010 '
b10001111011100001011000001010001 (
#350
0$
#351
1$
b10111000000000100001110100010011 &
b10111000000000100001110100010011 '
b00101000100100010110110011000010 (
#352
0$
#353
1$
b11100000100100111000100111010101 &
b11100000100100111000100111010101 '
b10111000000000100001110100010011 (
#354
0$
#355
1$
b10011000100101011010011011101000 &
b10011000100101011010011011101000 '
b11100000100100111000100111010101 (
#356
0$
#357
1$
b01111001001010010011000010111101 &
b01111001001010010011000010111101 '
b10011000100101011010011011101000 (
#358
0$
#359
1$
b00010001101111101101011110100101 &
b00010001101111101101011110100101 '
b01111001001010010011000010111101 (
#360
0$
#361
1$
b10001010111010000000100001100010 &
b10001010111010000000100001100010 '
b00010001101111101101011110100101 (
#362
0$
#363
1$
b10011100101001101110000000000111 &
b10011100101001101110000000000111 '
b10001010111010000000100001100010 (
#364
0$
#365
1$
b00100111100011101110100001101001 &
b00100111100011101110100001101001 '
b10011100101001101110000000000111 (
#366
0$
#367
1$
b11000100001101011100100001110000 &
b11000100001101011100100001110000 '
b00100111100011101110100001101001 (
#368
0$
#369
1$
b11101011110001001011000011011001 &
b11101011110001001011000011011001 '
b11000100001101011100100001110000 (
#370
0$
#371
1$
b10101111111110100111100101001001 &
b10101111111110100111100101001001 '
b11101011110001001011000011011001 (
#372
0$
#373
1$
b10011011101111110010101000100010 &
b10011011101111110010101000100010 '
b10101111111110100111100101001001 (
#374
0$
#375
1$
b01001011101110011010001101101011 &
b01001011101110011010001101101011 '
b10011011101111110010101000100010 (
#376
0$
#377
1$
b11100111011110001100110110001101 &
b11100111011110001100110110001101 '
b01001011101110011010001101101011 (
#378
0$
#379
1$
b00110011001100100111000011111000 &
b00110011001100100111000011111000 '
b11100111011110001100110110001101 (
#380
0$
#381
1$
b00011010101010110011111010000101 &
b00011010101010110011111010000101 '
b00110011001100100111000011111000 (
#382
0$
#383
1$
b01001101110111011010111101111101 &
b01001101110111011010111101111101 '
b00011010101010110011111010000101 (
#384
0$
#385
1$
b01101000100010001110111000000010 &
b01101000100010001110111000000010 '
b01001101110111011010111101111101 (
#386
0$
#387
1$
b10110110011001101001110101111111 &
b10110110011001101001110101111111 '
b01101000100010001110111000000010 (
#388
0$
#389
1$
b00011110111011111000101110000001 &
b00011110111011111000101110000001 '
b10110110011001101001110101111111 (
#390
0$
#391
1$
b11010101010101100010100100000000 &
b11010101010101100010100100000000 '
b00011110111011111000101110000001 (
#392
0$
#393
1$
b11110100010001011011010010000001 &
b11110100010001011011010010000001 '
b11010101010101100010100100000000 (
#394
0$
#395
1$
b11001001100110111101110110000001 &
b11001001100110111101110110000001 '
b11110100010001011011010010000001 (
#396
0$
#397
1$
b10111101111000011001001000000010 &
b10111101111000011001001000000010 '
b11001001100110111101110110000001 (
#398
0$
#399
1$
b10000111011111010110111110000011 &
b10000111011111010110111110000011 '
b10111101111000011001001000000010 (
#400
0$
#401
1$
b01000101010111110000000110000101 &
b01000101010111110000000110000101 '
b10000111011111010110111110000011 (
#402
0$
#403
1$
b11001100110111000111000100001000 &
b11001100110111000111000100001000 '
b01000101010111110000000110000101 (
#404
0$
#405
1$
b00010010001110110111001010001101 &
b00010010001110110111001010001101 '
b11001100110111000111000100001000 (
#406
0$
#407
1$
b11011111000101111110001110010101 &
b11011111000101111110001110010101 '
b00010010001110110111001010001101 (
#408
0$
#409
1$
b11110001010100110101011000100010 &
b11110001010100110101011000100010 '
b11011111000101111110001110010101 (
#410
0$
#411
1$
b11010000011010110011100110110111 &
b11010000011010110011100110110111 '
b11110001010100110101011000100010 (
#412
0$
#413
1$
b11000001101111101000111111011001 &
b11000001101111101000111111011001 '
b11010000011010110011100110110111 (
#414
0$
#415
1$
b10010010001010011100100110010000 &
b10010010001010011100100110010000 '
b11000001101111101000111111011001 (
#416
0$
#417
1$
b01010011111010000101100101101001 &
b01010011111010000101100101101001 '
b10010010001010011100100110010000 (
#418
0$
#419
1$
b11100110000100100010001011111001 &
b11100110000100100010001011111001 '
b01010011111010000101100101101001 (
#420
0$
#421
1$
b00111001111110100111110001100010 &
b00111001111110100111110001100010 '
b11100110000100100010001011111001 (
#422
0$
#423
1$
b00100000000011001001111101011011 &
b00100000000011001001111101011011 '
b00111001111110100111110001100010 (
#424
0$
#425
1$
b01011010000001110001101110111101 &
b01011010000001110001101110111101 '
b00100000000011001001111101011011 (
#426
0$
#427
1$
b01111010000100111011101100011000 &
b01111010000100111011101100011000 '
b01011010000001110001101110111101 (
#428
0$
#429
1$
b11010100000110101101011011010101 &
b11010100000110101101011011010101 '
b01111010000100111011101100011000 (
#430
0$
#431
1$
b01001110001011101001000111101101 &
b01001110001011101001000111101101 '
b11010100000110101101011011010101 (
#432
0$
#433
1$
b00100010010010010110100011000010 &
b00100010010010010110100011000010 '
b01001110001011101001000111101101 (
#434
0$
#435
1$
b01110000011101111111101010101111 &
b01110000011101111111101010101111 '
b00100010010010010110100011000010 (
#436
0$
#437
1$
b10010010110000010110001101110001 &
b10010010110000010110001101110001 '
b01110000011101111111101010101111 (
#438
0$
#439
1$
b00000011001110010101111000100000 &
b00000011001110010101111000100000 '
b10010010110000010110001101110001 (
#440
0$
#441
1$
b10010101111110101100000110010001 &
b10010101111110101100000110010001 '
b00000011001110010101111000100000 (
#442
0$
#443
1$
b10011001001101000001111110110001 &
b10011001001101000001111110110001 '
b10010101111110101100000110010001 (
#444
0$
#445
1$
b00101111001011101110000101000010 &
b00101111001011101110000101000010 '
b10011001001101000001111110110001 (
#446
0$
#447
1$
b11001000011000110000000011110011 &
b11001000011000110000000011110011 '
b00101111001011101110000101000010 (
#448
0$
#449
1$
b11110111100100011110001000110101 &
b11110111100100011110001000110101 '
b11001000011000110000000011110011 (
#450
0$
#451
1$
b10111111111101001110001100101000 &
b10111111111101001110001100101000 '
b11110111100100011110001000110101 (
#452
0$
#453
1$
b10110111100001101100010101011101 &
b10110111100001101100010101011101 '
b10111111111101001110001100101000 (
#454
0$
#455
1$
b01110111011110111010100010000101 &
b01110111011110111010100010000101 '
b10110111100001101100010101011101 (
#456
0$
#457
1$
b00101111000000100110110111100010 &
b00101111000000100110110111100010 '
b01110111011110111010100010000101 (
#458
0$
#459
1$
b10100110011111100001011001100111 &
b10100110011111100001011001100111 '
b00101111000000100110110111100010 (
#460
0$
#461
1$
b11010101100000001000010001001001 &
b11010101100000001000010001001001 '
b10100110011111100001011001100111 (
#462
0$
#463
1$
b01111011111111101001101010110000 &
b01111011111111101001101010110000 '
b11010101100000001000010001001001 (
#464
0$
#465
1$
b01010001011111110001111011111001 &
b01010001011111110001111011111001 '
b01111011111111101001101010110000 (
#466
0$
#467
1$
b11001101011111011011100110101001 &
b11001101011111011011100110101001 '
b01010001011111110001111011111001 (
#468
0$
#469
1$
b00011110111111001101100010100010 &
b00011110111111001101100010100010 '
b11001101011111011011100110101001 (
#470
0$
#471
1$
b11101100011110101001001001001011 &
b11101100011110101001001001001011 '
b00011110111111001101100010100010 (
#472
0$
#473
1$
b00001011011101110110101011101101 &
b00001011011101110110101011101101 '
b11101100011110101001001001001011 (
#474
0$
#475
1$
b11110111111100011111110100111000 &
b11110111111100011111110100111000 '
b00001011011101110110101011101101 (
#476
0$
#477
1$
b00000011011010010110100000100101 &
b00000011011010010110100000100101 '
b11110111111100011111110100111000 (
#478
0$
#479
1$
b11111011010110110110010101011101 &
b11111011010110110110010101011101 '
b00000011011010010110100000100101 (
#480
0$
#481
1$
b11111110110001001100110110000010 &
b11111110110001001100110110000010 '
b11111011010110110110010101011101 (
#482
0$
#483
1$
b11111010001000000011001011011111 &
b11111010001000000011001011011111 '
b11111110110001001100110110000010 (
#484
0$
#485
1$
b11111000111001010000000001100001 &
b11111000111001010000000001100001 '
b11111010001000000011001011011111 (
#486
0$
#487
1$
b11110011000001010011001101000000 &
b11110011000001010011001101000000 '
b11111000111001010000000001100001 (
#488
0$
#489
1$
b11101011111010100011001110100001 &
b11101011111010100011001110100001 '
b11110011000001010011001101000000 (
#490
0$
#491
1$
b11011110111011110110011011100001 &
b11011110111011110110011011100001 '
b11101011111010100011001110100001 (
#492
0$
#493
1$
b11001010110110011001101010000010 &
b11001010110110011001101010000010 '
b11011110111011110110011011100001 (
#494
0$
#495
1$
b10101001110010010000000101100011 &
b10101001110010010000000101100011 '
b11001010110110011001101010000010 (
#496
0$
#497
1$
b01110100101000101001101111100101 &
b01110100101000101001101111100101 '
b10101001110010010000000101100011 (
#498
0$
#499
1$
b00011110011010111001110101001000 &
b00011110011010111001110101001000 '
b01110100101000101001101111100101 (
#500
0$
#501
1$
b10010011000011100011100100101101 &
b10010011000011100011100100101101 '
b00011110011010111001110101001000 (
#502
0$
#503
1$
b10110001011110011101011001110101 &
b10110001011110011101011001110101 '
b10010011000011100011100100101101 (
#504
0$
#505
1$
b01000100100010000000111110100010 &
b01000100100010000000111110100010 '
b10110001011110011101011001110101 (
#506
0$
#507
1$
b11110110000000011110011000010111 &
b11110110000000011110011000010111 '
b01000100100010000000111110100010 (
#508
0$
#509
1$
b00111010100010011111010110111001 &
b00111010100010011111010110111001 '
b11110110000000011110011000010111 (
#510
0$
#511
1$
b00110000100010111101101111010000 &
b00110000100010111101101111010000 '
b00111010100010011111010110111001 (
#512
0$
